src/__init__.py
src/commands/__init__.py
src/commands/grawsp/__init__.py
src/commands/grawsp/actions/__init__.py
src/commands/grawsp/actions/aws.py
src/commands/grawsp/app.py
src/commands/grawsp/config.py
src/commands/grawsp/constants.py
src/commands/grawsp/controllers/__init__.py
src/commands/grawsp/controllers/about.py
src/commands/grawsp/controllers/auth.py
src/commands/grawsp/controllers/base.py
src/commands/grawsp/controllers/export.py
src/commands/grawsp/controllers/list.py
src/commands/grawsp/controllers/open_console.py
src/commands/grawsp/controllers/sync.py
src/commands/grawsp/database/__init__.py
src/commands/grawsp/database/models.py
src/commands/grawsp/defaults.py
src/commands/grawsp/exceptions.py
src/commands/grawsp/helpers.py
src/commands/grawsp/hooks.py
src/services/aws/__init__.py
src/services/aws/iam.py
src/services/aws/sso.py
src/services/aws/sts.py
src/util/__init__.py
src/util/terminal/__init__.py
src/util/terminal/spinner.py
grawsp-1.1.0.dist-info/LICENSE
grawsp-1.1.0.dist-info/METADATA
grawsp-1.1.0.dist-info/WHEEL
grawsp-1.1.0.dist-info/entry_points.txt
grawsp-1.1.0.dist-info/RECORD
